CHANGES.txt
CONTRIBUTORS.txt
MANIFEST.in
README.txt
setup.py
docs/LICENSE.GPL
docs/LICENSE.txt
silverpop/CHANGELOG
silverpop/README.txt
silverpop/__init__.py
silverpop/api.py
silverpop.egg-info/PKG-INFO
silverpop.egg-info/SOURCES.txt
silverpop.egg-info/dependency_links.txt
silverpop.egg-info/entry_points.txt
silverpop.egg-info/not-zip-safe
silverpop.egg-info/top_level.txt
silverpop/tests/__init__.py
silverpop/tests/test_docs.py