Metadata-Version: 1.0
Name: silverpop
Version: 0.2
Summary: API for Silverpop Enterprise Newslettering
Home-page: https://silverpop.googlecode.com/svn/tags/0.2
Author: Hans-Peter Locher
Author-email: hans-peter.locher@inquant.de
License: GPL
Keywords: Silverpop API
Platform: UNKNOWN
Classifier: Intended Audience :: Developers
Classifier: Topic :: Software Development :: Libraries :: Python Modules
Classifier: License :: OSI Approved :: GNU General Public License (GPL)
